ztb_access_control/__init__.py
ztb_access_control/auth_client.py
ztb_access_control/cerbos_client.py
ztb_access_control/config.py
ztb_access_control/dependencies.py
ztb_access_control/exceptions.py
ztb_access_control/models.py
ztb_access_control/schema.py
ztb_access_control/token_manager.py
zerotb_ai_ztb_access_control-0.1.0.dist-info/METADATA
zerotb_ai_ztb_access_control-0.1.0.dist-info/WHEEL
zerotb_ai_ztb_access_control-0.1.0.dist-info/top_level.txt
zerotb_ai_ztb_access_control-0.1.0.dist-info/RECORD
