Metadata-Version: 2.4
Name: zerotb-ai-ztb_access_control
Version: 0.1.0
Summary: Shared authentication and authorization client for ZTB microservices
Project-URL: Homepage, https://github.com/your-org/ztb-access-control
Project-URL: Repository, https://github.com/your-org/ztb-access-control
Classifier: Development Status :: 3 - Alpha
Classifier: Intended Audience :: Developers
Classifier: License :: OSI Approved :: MIT License
Classifier: Programming Language :: Python :: 3.13
Requires-Python: >=3.8
Requires-Dist: fastapi>=0.100.0
Requires-Dist: pyjwt[crypto]>=2.8.0
Requires-Dist: cerbos>=0.7.0
Requires-Dist: pydantic>=2.0.0
Requires-Dist: httpx>=0.24.0
Requires-Dist: python-multipart>=0.0.6
Requires-Dist: cryptography>=41.0.0
Provides-Extra: dev
Requires-Dist: pytest>=7.0.0; extra == "dev"
Requires-Dist: pytest-asyncio>=0.21.0; extra == "dev"
Requires-Dist: black>=23.0.0; extra == "dev"
Requires-Dist: isort>=5.12.0; extra == "dev"
Requires-Dist: mypy>=1.5.0; extra == "dev"
